didsdk/__about__.py
didsdk/__init__.py
didsdk/config.py
didsdk/credential.py
didsdk/did_service.py
didsdk/presentation.py
didsdk/vc_service.py
didsdk/core/__init__.py
didsdk/core/algorithm.py
didsdk/core/algorithm_provider.py
didsdk/core/did_key_holder.py
didsdk/core/es256k_algorithm.py
didsdk/core/key_provider.py
didsdk/core/key_store.py
didsdk/core/none_algorithm.py
didsdk/core/property_name.py
didsdk/document/__init__.py
didsdk/document/authentication_property.py
didsdk/document/document.py
didsdk/document/encoding.py
didsdk/document/publickey_property.py
didsdk/exceptions/__init__.py
didsdk/jwe/__init__.py
didsdk/jwe/ecdhkey.py
didsdk/jwe/ephemeral_publickey.py
didsdk/jwt/__init__.py
didsdk/jwt/convert_jwt.py
didsdk/jwt/elements.py
didsdk/jwt/issuer_did.py
didsdk/jwt/jwt.py
didsdk/protocol/__init__.py
didsdk/protocol/base_claim.py
didsdk/protocol/base_param.py
didsdk/protocol/base_vc.py
didsdk/protocol/claim_attribute.py
didsdk/protocol/claim_message_type.py
didsdk/protocol/claim_request.py
didsdk/protocol/claim_response.py
didsdk/protocol/hash_attribute.py
didsdk/protocol/presentation_request.py
didsdk/protocol/protocol_message.py
didsdk/protocol/protocol_type.py
didsdk/protocol/response_result.py
didsdk/protocol/json_ld/__init__.py
didsdk/protocol/json_ld/base_json_ld.py
didsdk/protocol/json_ld/claim.py
didsdk/protocol/json_ld/display_layout.py
didsdk/protocol/json_ld/info_param.py
didsdk/protocol/json_ld/json_ld_param.py
didsdk/protocol/json_ld/json_ld_util.py
didsdk/protocol/json_ld/json_ld_vc.py
didsdk/protocol/json_ld/json_ld_vcr.py
didsdk/protocol/json_ld/json_ld_vp.py
didsdk/protocol/json_ld/json_ld_vpr.py
didsdk/protocol/json_ld/revocation_service.py
didsdk/protocol/json_ld/vp_criteria.py
didsdk/protocol/json_ld/vpr_condition.py
didsdk/score/__init__.py
didsdk/score/did_score.py
didsdk/score/did_score_parameter.py
didsdk/score/vc_score.py
didsdk/score/vc_score_parameter.py
did_sdk_python-1.1.3.dist-info/METADATA
did_sdk_python-1.1.3.dist-info/WHEEL
did_sdk_python-1.1.3.dist-info/RECORD
