Metadata-Version: 2.4
Name: did-sdk-python
Version: 1.1.3
Summary: This SDK is used not only to create and manage ICON DID, but also to issue and verify credentials and presentations.
Project-URL: Documentation, https://github.com/iconloop/did-sdk-python#readme
Project-URL: Issues, https://github.com/iconloop/did-sdk-python/issues
Project-URL: Source, https://github.com/iconloop/did-sdk-python
Author-email: PARAMETA Corp <t_pds@parametacorp.com>
License-Expression: MIT
Classifier: Development Status :: 4 - Beta
Classifier: Programming Language :: Python
Classifier: Programming Language :: Python :: 3.10
Classifier: Programming Language :: Python :: 3.11
Classifier: Programming Language :: Python :: Implementation :: CPython
Requires-Python: <3.12,>=3.10
Requires-Dist: ecdsa[gmpy2]==0.18.0
Requires-Dist: iconsdk>=2.6.0
Requires-Dist: joserfc~=1.0.0
Requires-Dist: loguru~=0.7.2
Requires-Dist: pydantic-settings>=2.9.1
Requires-Dist: pydantic==2.11.4
Requires-Dist: setuptools>=80.9.0
Requires-Dist: validators==0.21.2
Provides-Extra: all
Requires-Dist: anyio[trio]~=3.7.0; extra == 'all'
Requires-Dist: pytest-cov~=4.0.0; extra == 'all'
Requires-Dist: pytest-mock~=3.10.0; extra == 'all'
Requires-Dist: pytest-recording~=0.13.2; extra == 'all'
Requires-Dist: pytest~=7.2.2; extra == 'all'
Requires-Dist: vcrpy==7.0.0; extra == 'all'
Provides-Extra: dev
Requires-Dist: anyio[trio]~=3.7.0; extra == 'dev'
Requires-Dist: pytest-cov~=4.0.0; extra == 'dev'
Requires-Dist: pytest-mock~=3.10.0; extra == 'dev'
Requires-Dist: pytest-recording~=0.13.2; extra == 'dev'
Requires-Dist: pytest~=7.2.2; extra == 'dev'
Requires-Dist: vcrpy==7.0.0; extra == 'dev'
